wsba_nhl_scraper/__init__.py
wsba_nhl_scraper/data_scrape.py
wsba_nhl_scraper/wsba_nhl_scrape.py
wsba_nhl_scraper-0.1.8.dist-info/LICENSE
wsba_nhl_scraper-0.1.8.dist-info/METADATA
wsba_nhl_scraper-0.1.8.dist-info/WHEEL
wsba_nhl_scraper-0.1.8.dist-info/top_level.txt
wsba_nhl_scraper-0.1.8.dist-info/RECORD
