Metadata-Version: 2.2
Name: wsba_nhl_scraper
Version: 0.1.8
Summary: A Python Package for scraping National Hockey League schedule, play-by-play, and shifts information.
Author-email: Owen Singh <owenbksingh@gmail.com>
Classifier: Programming Language :: Python :: 3
Classifier: License :: OSI Approved :: MIT License
Classifier: Operating System :: OS Independent
Requires-Python: >=3.8
License-File: LICENSE
